clusternet/__init__.py
clusternet/apis/__init__.py
clusternet/apis/presentation/__init__.py
clusternet/apis/presentation/exceptions.py
clusternet/apis/presentation/helpers.py
clusternet/apis/presentation/protocols.py
clusternet/apis/worker/__init__.py
clusternet/apis/worker/data.py
clusternet/apis/worker/helpers.py
clusternet/apis/worker/controllers/__init__.py
clusternet/apis/worker/controllers/add_controller.py
clusternet/apis/worker/controllers/add_docker.py
clusternet/apis/worker/controllers/add_link.py
clusternet/apis/worker/controllers/add_switch.py
clusternet/apis/worker/controllers/clean_containers.py
clusternet/apis/worker/controllers/config_default.py
clusternet/apis/worker/controllers/get_docker_ip.py
clusternet/apis/worker/controllers/remove_docker.py
clusternet/apis/worker/controllers/remove_link.py
clusternet/apis/worker/controllers/run_command.py
clusternet/apis/worker/controllers/run_pingall.py
clusternet/apis/worker/controllers/run_service.py
clusternet/apis/worker/controllers/start_docker.py
clusternet/apis/worker/controllers/start_worker.py
clusternet/apis/worker/controllers/stop_docker.py
clusternet/apis/worker/controllers/stop_worker.py
clusternet/apis/worker/controllers/update_cpu.py
clusternet/apis/worker/controllers/update_memory.py
clusternet/client/__init__.py
clusternet/client/container.py
clusternet/client/worker.py
clusternet/grafana/grafana.ini
clusternet/grafana/dashboards/dashboard.yml
clusternet/grafana/dashboards/docker.json
clusternet/grafana/datasources/datasource.yml
clusternet/monitoring/__init__.py
clusternet/monitoring/cluster.py
clusternet/monitoring/helpers.py
clusternet/monitoring/services.py
clusternet/server/__init__.py
clusternet/server/worker_app.py
clusternet-0.9.2.dist-info/METADATA
clusternet-0.9.2.dist-info/WHEEL
clusternet-0.9.2.dist-info/entry_points.txt
clusternet-0.9.2.dist-info/top_level.txt
clusternet-0.9.2.dist-info/RECORD
